fast_stats-1.3.2.dist-info/METADATA
fast_stats-1.3.2.dist-info/WHEEL
fast_stats-1.3.2.dist-info/license_files/LICENSE
fast_stats/binary.py
fast_stats/_fast_stats_ext.pyi
fast_stats/multiclass.py
fast_stats/__init__.py
fast_stats/exceptions.py
fast_stats/iou.py
fast_stats/confusion_matrix.py
fast_stats/_fast_stats_ext.cpython-38-darwin.so
fast_stats-1.3.2.dist-info/RECORD
