Metadata-Version: 2.1
Name: fast-stats
Version: 1.3.2
Classifier: Programming Language :: Rust
Classifier: Programming Language :: Python :: Implementation :: CPython
Classifier: Programming Language :: Python :: 3.7
Classifier: Programming Language :: Python :: 3.8
Classifier: Programming Language :: Python :: 3.9
Classifier: Programming Language :: Python :: 3.10
Classifier: Programming Language :: Python :: 3.11
Requires-Dist: numpy
Requires-Dist: bump2version; extra == 'dev'
Requires-Dist: dictdiffer; extra == 'dev'
Requires-Dist: pre-commit; extra == 'dev'
Requires-Dist: pytest; extra == 'dev'
Requires-Dist: pytest-cov[all]; extra == 'dev'
Provides-Extra: dev
License-File: LICENSE
Summary: A fast and simple library for calculating basic statistics
Keywords: numpy,stats,rust,fast
Author: Zach Coleman
Author-email: zacharywcoleman@gmail.com
License: Apache 2.0
Requires-Python: >=3.7
Project-URL: repository, https://github.com/zachcoleman/fast-stats
